RenameStringsInFile/Renamer.py
RenameStringsInFile/__init__.py
RenamerSeventhSon-0.0.1.dist-info/METADATA
RenamerSeventhSon-0.0.1.dist-info/WHEEL
RenamerSeventhSon-0.0.1.dist-info/top_level.txt
RenamerSeventhSon-0.0.1.dist-info/RECORD
