Metadata-Version: 2.1
Name: RenamerSeventhSon
Version: 0.0.1
Summary: rename things into files
Home-page: UNKNOWN
Author: 
Author-email: 
License: UNKNOWN
Keywords: python,renemae yeah
Platform: UNKNOWN
Classifier: Development Status :: 1 - Planning
Classifier: Intended Audience :: Developers
Classifier: Programming Language :: Python :: 3
Classifier: Operating System :: Unix
Classifier: Operating System :: MacOS :: MacOS X
Classifier: Operating System :: Microsoft :: Windows
